README.md
setup.py
pybalebot/__init__.py
pybalebot/api.py
pybalebot/client.py
pybalebot/errors.py
pybalebot/filters.py
pybalebot.egg-info/PKG-INFO
pybalebot.egg-info/SOURCES.txt
pybalebot.egg-info/dependency_links.txt
pybalebot.egg-info/requires.txt
pybalebot.egg-info/top_level.txt
pybalebot/methods/__init__.py
pybalebot/methods/chats/__init__.py
pybalebot/methods/chats/ban_chat_member.py
pybalebot/methods/chats/export_chat_invite_link.py
pybalebot/methods/chats/get_chat.py
pybalebot/methods/chats/get_chat_administrators.py
pybalebot/methods/chats/get_chat_member.py
pybalebot/methods/chats/get_chat_member_count.py
pybalebot/methods/chats/leave_chat.py
pybalebot/methods/chats/promote_chat_member.py
pybalebot/methods/chats/send_chat_action.py
pybalebot/methods/chats/set_chat_photo.py
pybalebot/methods/chats/unban_chat_member.py
pybalebot/methods/invoices/__init__.py
pybalebot/methods/invoices/send_nvoice.py
pybalebot/methods/messages/__init__.py
pybalebot/methods/messages/copy_message.py
pybalebot/methods/messages/delete_message.py
pybalebot/methods/messages/edit_message_caption.py
pybalebot/methods/messages/edit_message_text.py
pybalebot/methods/messages/forward_message.py
pybalebot/methods/messages/pin_chat_message.py
pybalebot/methods/messages/send_animation.py
pybalebot/methods/messages/send_audio.py
pybalebot/methods/messages/send_contact.py
pybalebot/methods/messages/send_document.py
pybalebot/methods/messages/send_location.py
pybalebot/methods/messages/send_media_group.py
pybalebot/methods/messages/send_message.py
pybalebot/methods/messages/send_photo.py
pybalebot/methods/messages/send_poll.py
pybalebot/methods/messages/send_video.py
pybalebot/methods/messages/send_voice.py
pybalebot/methods/others/__init__.py
pybalebot/methods/others/answer_callback_query.py
pybalebot/methods/others/answer_inline_query.py
pybalebot/methods/others/close.py
pybalebot/methods/others/download.py
pybalebot/methods/others/get_file.py
pybalebot/methods/others/logout.py
pybalebot/methods/stickers/__init__.py
pybalebot/methods/stickers/add_sticker_to_set.py
pybalebot/methods/stickers/create_new_sticker_set.py
